AUTHORS.txt
COPYING.txt
MANIFEST.in
NEWS.rst
README.rst
netzob
pyproject.toml
requirements.txt
setup.cfg
setup.py
lib/argsFactories/factory.c
lib/includes/Interface.h
lib/includes/Needleman.h
lib/includes/clusterBySnappy.h
lib/includes/commonLib.h
lib/includes/factory.h
lib/includes/relation.h
lib/includes/scoreComputation.h
lib/includes/struct.h
lib/includes/Py_lib/commonPythonLib.h
lib/includes/Py_lib/libInterface.h
lib/includes/Py_lib/libNeedleman.h
lib/includes/Py_lib/libRelation.h
lib/includes/Py_lib/libScoreComputation.h
lib/interface/Interface.c
lib/interface/Py_lib/libInterface.c
lib/libNeedleman/Needleman.c
lib/libNeedleman/scoreComputation.c
lib/libNeedleman/Py_lib/libNeedleman.c
lib/libNeedleman/Py_lib/libScoreComputation.c
lib/libRelation/relation.c
lib/libRelation/Py_lib/libRelation.c
lib/libRelation/algorithms/Makefile
lib/libRelation/algorithms/rel_equality.c
lib/libRelation/algorithms/rel_size.c
lib/libRelation/algorithms/rel_test.c
lib/tools/getBID.c
resources/__init__.py
resources/dockerbuild/Dockerfile
resources/dockerbuild/README.md
resources/epydoc/config
resources/quality/clean-netzob.sh
resources/quality/coverage/python-coverage.conf
resources/quality/git-hooks/pre-commit.py
resources/quality/pylint/config
resources/quality/tox/tox.ini
resources/sdist/__init__.py
resources/sdist/babel_extract.py
resources/sdist/manpage_command.py
resources/sdist/test_command.py
resources/sdist/utils.py
src/Netzob.egg-info/PKG-INFO
src/Netzob.egg-info/SOURCES.txt
src/Netzob.egg-info/dependency_links.txt
src/Netzob.egg-info/requires.txt
src/Netzob.egg-info/top_level.txt
src/netzob/NetzobInteractiveSessionController.py
src/netzob/NetzobResources.py
src/netzob/__init__.py
src/netzob/all.py
src/netzob/conf.py
src/netzob/release.py
src/netzob/Common/CommandLine.py
src/netzob/Common/DepCheck.py
src/netzob/Common/LoggingConfiguration.py
src/netzob/Common/NetzobException.py
src/netzob/Common/__init__.py
src/netzob/Common/all.py
src/netzob/Common/C_Extensions/WrapperArgsFactory.py
src/netzob/Common/C_Extensions/WrapperMessage.py
src/netzob/Common/C_Extensions/__init__.py
src/netzob/Common/Utils/Constant.py
