Metadata-Version: 2.1
Name: Netzob
Version: 2.0.0
Summary: Protocol Reverse Engineering, Modeling and Fuzzing
Home-page: https://github.com/netzob/netzob
Download-URL: https://github.com/netzob/netzob
Author: Georges Bossert, Frédéric Guihéry
License: GPLv3
Keywords: Protocol,Inference,Networking,Reverse Engineering,Fuzzing,Security
Platform: Linux_x86
Platform: Linux_x64
Classifier: Programming Language :: Python
Classifier: Programming Language :: Python :: 3
Classifier: Programming Language :: C
Classifier: Development Status :: 4 - Beta
Classifier: Intended Audience :: Developers
Classifier: Intended Audience :: Science/Research
Classifier: Intended Audience :: System Administrators
Classifier: License :: OSI Approved :: GNU General Public License (GPL)
Classifier: Operating System :: OS Independent
Classifier: Natural Language :: English
Classifier: Topic :: Security
Classifier: Topic :: System :: Networking
License-File: COPYING.txt
License-File: AUTHORS.txt
